asgard_lab_DM_tools/17DW019#053_FLAT_MAP_COMMANDS.txt
asgard_lab_DM_tools/17DW019#093_FLAT_MAP_COMMANDS.txt
asgard_lab_DM_tools/17DW019#113_FLAT_MAP_COMMANDS.txt
asgard_lab_DM_tools/17DW019#122_FLAT_MAP_COMMANDS.txt
asgard_lab_DM_tools/__init__.py
asgard_lab_DM_tools/asgard_lab_DM_controller.py
asgard_lab_DM_tools/asgard_lab_MDM_controller.py
asgard_lab_DM_tools/turbulence_simulator.py
asgard_lab_dm_tools-0.0.10.dist-info/METADATA
asgard_lab_dm_tools-0.0.10.dist-info/WHEEL
asgard_lab_dm_tools-0.0.10.dist-info/entry_points.txt
asgard_lab_dm_tools-0.0.10.dist-info/licenses/LICENSE
asgard_lab_dm_tools-0.0.10.dist-info/RECORD
