Metadata-Version: 2.4
Name: asgard_lab_DM_tools
Version: 0.0.10
Summary: Tools to interact with the Asgard BMC DMs in lab
Project-URL: Homepage, https://github.com/fmartinache/asgard_lab_DM_controller/
Project-URL: Issues, https://github.com/fmartinache/asgard_lab_DM_controller/issues
Author-email: Frantz Martinache <frantz.martinache@oca.eu>
License-File: LICENSE
Classifier: License :: OSI Approved :: MIT License
Classifier: Operating System :: POSIX :: Linux
Classifier: Programming Language :: Python :: 3
Requires-Python: >=3.9
Requires-Dist: numpy
Requires-Dist: pyqt5
Requires-Dist: pyqtgraph
Requires-Dist: qtpy
Requires-Dist: xaosim
